clicker_bot/__init__.py
clicker_bot/__main__.py
clicker_bot/py.typed
clicker_bot/command/__init__.py
clicker_bot/command/respond.py
clicker_bot/datapack/__init__.py
clicker_bot/onebot/__init__.py
clicker_bot/storage/__init__.py
clicker_bot/util/__init__.py
clicker_bot-0.0.1.dist-info/METADATA
clicker_bot-0.0.1.dist-info/WHEEL
clicker_bot-0.0.1.dist-info/RECORD
