Metadata-Version: 2.4
Name: clicker-bot
Version: 0.0.1
Summary: A framework for clicker bot based on Onebot V11
Author-email: BrokenC1oud <jgbsxx20130315@gmail.com>
Requires-Python: >=3.13
Requires-Dist: flask-sqlalchemy==3.1.1
Requires-Dist: flask==3.1.1
Requires-Dist: hatchling>=1.27.0
Requires-Dist: pydantic==2.11.5
